hamqtt_fs_publisher/__init__.py
hamqtt_fs_publisher/__main__.py
hamqtt_fs_publisher/configuration.py
hamqtt_fs_publisher/configuration.schema.json
hamqtt_fs_publisher-0.1.3.dist-info/LICENSE
hamqtt_fs_publisher-0.1.3.dist-info/METADATA
hamqtt_fs_publisher-0.1.3.dist-info/WHEEL
hamqtt_fs_publisher-0.1.3.dist-info/entry_points.txt
hamqtt_fs_publisher-0.1.3.dist-info/RECORD
