Metadata-Version: 2.1
Name: hamqtt-fs-publisher
Version: 0.1.3
Summary: Publish file content as MQTT topic compatible with HomeAssistant.
Home-page: https://github.com/MarekPikula/homeassistant-mqtt-filesystem-publisher
License: MIT
Author: Marek Pikuła
Author-email: marek@serenitycode.dev
Maintainer: Marek Pikuła
Maintainer-email: marek@serenitycode.dev
Requires-Python: >=3.8,<4.0
Classifier: Development Status :: 3 - Alpha
Classifier: License :: OSI Approved :: MIT License
Classifier: Operating System :: OS Independent
Classifier: Programming Language :: Python :: 3
Classifier: Programming Language :: Python :: 3.8
Classifier: Programming Language :: Python :: 3.9
Classifier: Programming Language :: Python :: 3.10
Classifier: Programming Language :: Python :: 3.11
Provides-Extra: pyyaml
Provides-Extra: ruamel
Requires-Dist: click (>=8.1.3,<9.0.0)
Requires-Dist: homeassistant-mqtt-binding (>=2.0.2,<3.0.0)
Requires-Dist: loguru (>=0.7.0,<0.8.0)
Requires-Dist: pydantic (>=1.10.7,<2.0.0)
Requires-Dist: pydantic-yaml (>=0.11.2,<0.12.0) ; extra == "ruamel" or extra == "pyyaml"
Requires-Dist: pyyaml (>=6.0,<7.0) ; extra == "pyyaml"
Requires-Dist: ruamel-yaml (>=0.17.24,<0.18.0) ; extra == "ruamel"
Project-URL: Repository, https://github.com/MarekPikula/homeassistant-mqtt-filesystem-publisher
